ephypype/__init__.py
ephypype/aux_tools.py
ephypype/compute_fwd_problem.py
ephypype/compute_inv_problem.py
ephypype/datasets.py
ephypype/fif2array.py
ephypype/import_data.py
ephypype/power.py
ephypype/preproc.py
ephypype/source_estimate.py
ephypype/source_space.py
ephypype/spectral.py
ephypype/commands/__init__.py
ephypype/commands/neuropycon.py
ephypype/externals/__init__.py
ephypype/externals/click/__init__.py
ephypype/externals/click/_bashcomplete.py
ephypype/externals/click/_compat.py
ephypype/externals/click/_termui_impl.py
ephypype/externals/click/_textwrap.py
ephypype/externals/click/_unicodefun.py
ephypype/externals/click/_winconsole.py
ephypype/externals/click/core.py
ephypype/externals/click/decorators.py
ephypype/externals/click/exceptions.py
ephypype/externals/click/formatting.py
ephypype/externals/click/globals.py
ephypype/externals/click/parser.py
ephypype/externals/click/termui.py
ephypype/externals/click/testing.py
ephypype/externals/click/types.py
ephypype/externals/click/utils.py
ephypype/gather/__init__.py
ephypype/gather/gather_conmats.py
ephypype/gather/gather_results.py
ephypype/interfaces/__init__.py
ephypype/interfaces/mne/Inverse_solution.py
ephypype/interfaces/mne/LF_computation.py
ephypype/interfaces/mne/__init__.py
ephypype/interfaces/mne/power.py
ephypype/interfaces/mne/preproc.py
ephypype/interfaces/mne/spectral.py
ephypype/nodes/FT_tools.py
ephypype/nodes/__init__.py
ephypype/nodes/import_data.py
ephypype/nodes/power_tools.py
ephypype/nodes/ts_tools.py
ephypype/nodes/utils.py
ephypype/pipelines/__init__.py
ephypype/pipelines/brain_vision_to_conmat.py
ephypype/pipelines/fif_to_inv_sol.py
ephypype/pipelines/power.py
ephypype/pipelines/preproc_meeg.py
ephypype/pipelines/ts_to_conmat.py
ephypype-0.7.dist-info/LICENSE
ephypype-0.7.dist-info/METADATA
ephypype-0.7.dist-info/WHEEL
ephypype-0.7.dist-info/entry_points.txt
ephypype-0.7.dist-info/top_level.txt
ephypype-0.7.dist-info/RECORD
