Metadata-Version: 2.2
Name: ephypype
Version: 0.7
Summary: Python package providing pipelines for electrophysiological (EEG/MEG) data within nipype framework.
Home-page: https://neuropycon.github.io/ephypype/
Download-URL: https://github.com/neuropycon/ephypype
Author: ['David Meunier', 'Annalisa Pascarella', 'Dmitrii Altukhov']
Maintainer: Annalisa Pascarella
Maintainer-email: a.pascarella@iac.cnr.it
License: BSD (3-clause)
License-File: LICENSE
Requires-Dist: nipype
Requires-Dist: networkx>=2.0
Requires-Dist: numpy
Requires-Dist: mne
Requires-Dist: pybids
Requires-Dist: h5py
Requires-Dist: scikit-learn
Requires-Dist: matplotlib
Requires-Dist: mne-bids
Requires-Dist: mne_connectivity
Dynamic: author
Dynamic: description
Dynamic: description-content-type
Dynamic: download-url
Dynamic: home-page
Dynamic: license
Dynamic: maintainer
Dynamic: maintainer-email
Dynamic: requires-dist
Dynamic: summary
